endstone_home_pilot/__init__.py
endstone_home_pilot/config.py
endstone_home_pilot/database_controller.py
endstone_home_pilot/main.py
endstone_home_pilot-0.0.1.dist-info/METADATA
endstone_home_pilot-0.0.1.dist-info/WHEEL
endstone_home_pilot-0.0.1.dist-info/entry_points.txt
endstone_home_pilot-0.0.1.dist-info/RECORD
