Metadata-Version: 2.3
Name: endstone-home-pilot
Version: 0.0.1
Summary: A Home Pilot for endstone servers!
